codex/__init__.py
codex/cli_agent.py
codex/cli_commands.py
codex/cli_core.py
codex/database.py
codex/log_config.py
codex/suggestions.py
codex/integrations/__init__.py
codex/integrations/github.py
codex/integrations/google.py
codex/integrations/stackoverflow.py
codex/integrations/wikipedia.py
codex/integrations/wolframalpha.py
codex/locales/__init__.py
codex/locales/i18n.py
codex_cli_montezuma-0.1.5.dist-info/licenses/LICENSE
codex_cli_montezuma-0.1.5.dist-info/METADATA
codex_cli_montezuma-0.1.5.dist-info/WHEEL
codex_cli_montezuma-0.1.5.dist-info/entry_points.txt
codex_cli_montezuma-0.1.5.dist-info/top_level.txt
codex_cli_montezuma-0.1.5.dist-info/RECORD
