Metadata-Version: 2.4
Name: codex-cli-montezuma
Version: 0.1.5
Summary: Codex CLI – Ferramentas de IA, APIs e automação para desenvolvedores. Modular, extensível, com logging, testes e documentação de referência.
Author-email: montezuma <pedromontezuma@gmail.com>
Keywords: cli,ia,automacao,desenvolvedores,aplicativo,codex
Classifier: Programming Language :: Python :: 3
Classifier: License :: OSI Approved :: MIT License
Classifier: Operating System :: OS Independent
Classifier: Intended Audience :: Developers
Classifier: Topic :: Software Development :: Libraries :: Application Frameworks
Classifier: Topic :: Utilities
Requires-Python: >=3.9
License-File: LICENSE
Requires-Dist: requests
Requires-Dist: sqlalchemy
Requires-Dist: google-genai
Requires-Dist: google-api-python-client
Requires-Dist: google-auth
Requires-Dist: google-auth-oauthlib
Requires-Dist: google-auth-httplib2
Provides-Extra: dev
Requires-Dist: pytest; extra == "dev"
Requires-Dist: pytest-cov; extra == "dev"
Requires-Dist: build; extra == "dev"
Requires-Dist: twine; extra == "dev"
Requires-Dist: flake8; extra == "dev"
Dynamic: license-file
